{
  "coverageEntries": [
    {
      "id": "6903f5ed790cf57f776f5269",
      "fieldData": {
        "name": "Comcast",
        "slug": "comcast",
        "coverage-type": "Employer",
        "payer-parameter": "",
        "insurance-directory-slug": "",
        "coverage-notes": "",
        "is-insurance-census-less": "No",
        "requires-state-confirmation": "No",
        "require-state": "No",
        "supported-states": []
      }
    },
    {
      "id": "6903f634ad58ab7c941b772f",
      "fieldData": {
        "name": "Ibx",
        "slug": "ibx",
        "coverage-type": "Insurance",
        "payer-parameter": "ibx",
        "insurance-directory-slug": "",
        "coverage-notes": "",
        "is-insurance-census-less": "Yes",
        "requires-state-confirmation": "No",
        "require-state": "No",
        "supported-states": []
      }
    },
    {
      "id": "6903f4296b4ed1be1a5c1a9b",
      "fieldData": {
        "name": "Microsoft",
        "slug": "microsoft",
        "coverage-type": "Employer",
        "payer-parameter": "",
        "insurance-directory-slug": "",
        "coverage-notes": "",
        "is-insurance-census-less": "No",
        "requires-state-confirmation": "No",
        "require-state": "No",
        "supported-states": []
      }
    },
    {
      "id": "6903f69f2fcf06c4e16f3da8",
      "fieldData": {
        "name": "Premera Blue Cross",
        "slug": "premera-blue-cross",
        "coverage-type": "Insurance",
        "payer-parameter": "",
        "insurance-directory-slug": "premera_blue_cross",
        "coverage-notes": "<h3>Premera Blue Cross</h3><p>This is test data</p>",
        "is-insurance-census-less": "No",
        "requires-state-confirmation": "Yes",
        "require-state": "No",
        "supported-states": [
          {
            "id": "6903f2bb61067fc1c6d7fb6e",
            "fieldData": {
              "name": "Alabama",
              "slug": "alabama",
              "state-abbreviation": "AL",
              "active": "Yes"
            }
          },
          {
            "id": "6903f2bba5cea9e46a1b81a0",
            "fieldData": {
              "name": "Alaska",
              "slug": "alaska",
              "state-abbreviation": "AK",
              "active": "Yes"
            }
          },
          {
            "id": "6903f2bb1d424b4a1a376d34",
            "fieldData": {
              "name": "Arizona",
              "slug": "arizona",
              "state-abbreviation": "AZ",
              "active": "Yes"
            }
          },
          {
            "id": "6903f2bbca460d320710a892",
            "fieldData": {
              "name": "Arkansas",
              "slug": "arkansas",
              "state-abbreviation": "AR",
              "active": "Yes"
            }
          },
          {
            "id": "6903f2bb5ff0e3f9d4ab016f",
            "fieldData": {
              "name": "California",
              "slug": "california",
              "state-abbreviation": "CA",
              "active": "Yes"
            }
          },
          {
            "id": "6903f2bb99b332631b236e96",
            "fieldData": {
              "name": "Colorado",
              "slug": "colorado",
              "state-abbreviation": "CO",
              "active": "Yes"
            }
          },
          {
            "id": "6903f2bb99664e0c44ef277e",
            "fieldData": {
              "name": "Connecticut",
              "slug": "connecticut",
              "state-abbreviation": "CT",
              "active": "Yes"
            }
          },
          {
            "id": "6903f2bbcd5ca7439133df56",
            "fieldData": {
              "name": "Delaware",
              "slug": "delaware",
              "state-abbreviation": "DE",
              "active": "Yes"
            }
          },
          {
            "id": "6903f2bc65f00e82f49cf2e1",
            "fieldData": {
              "name": "Florida",
              "slug": "florida",
              "state-abbreviation": "FL",
              "active": "Yes"
            }
          },
          {
            "id": "6903f2bc8e3d219e4a3e1726",
            "fieldData": {
              "name": "Georgia",
              "slug": "georgia",
              "state-abbreviation": "GA",
              "active": "Yes"
            }
          },
          {
            "id": "6903f2bc13541897ea4b4b46",
            "fieldData": {
              "name": "Hawaii",
              "slug": "hawaii",
              "state-abbreviation": "HI",
              "active": "Yes"
            }
          },
          {
            "id": "6903f2bcab773ab938af6932",
            "fieldData": {
              "name": "Idaho",
              "slug": "idaho",
              "state-abbreviation": "ID",
              "active": "Yes"
            }
          },
          {
            "id": "6903f2bc0bb690eff3c64cae",
            "fieldData": {
              "name": "Illinois",
              "slug": "illinois",
              "state-abbreviation": "IL",
              "active": "Yes"
            }
          },
          {
            "id": "6903f2bce0e9a3a8b49d1ba7",
            "fieldData": {
              "name": "Indiana",
              "slug": "indiana",
              "state-abbreviation": "IN",
              "active": "Yes"
            }
          },
          {
            "id": "6903f2bce3db62b4cd45cd59",
            "fieldData": {
              "name": "Iowa",
              "slug": "iowa",
              "state-abbreviation": "IA",
              "active": "Yes"
            }
          },
          {
            "id": "6903f2bc560c699c97edcb89",
            "fieldData": {
              "name": "Kansas",
              "slug": "kansas",
              "state-abbreviation": "KS",
              "active": "Yes"
            }
          },
          {
            "id": "6903f2bc144e670775c51faf",
            "fieldData": {
              "name": "Kentucky",
              "slug": "kentucky",
              "state-abbreviation": "KY",
              "active": "Yes"
            }
          },
          {
            "id": "6903f2bcd657eab6424a41a6",
            "fieldData": {
              "name": "Louisiana",
              "slug": "louisiana",
              "state-abbreviation": "LA",
              "active": "Yes"
            }
          },
          {
            "id": "6903f2bc33a9c63289784a1e",
            "fieldData": {
              "name": "Maine",
              "slug": "maine",
              "state-abbreviation": "ME",
              "active": "Yes"
            }
          },
          {
            "id": "6903f2bceee62ad401683ca3",
            "fieldData": {
              "name": "Maryland",
              "slug": "maryland",
              "state-abbreviation": "MD",
              "active": "Yes"
            }
          },
          {
            "id": "6903f2bc1c1d5520d5cd133a",
            "fieldData": {
              "name": "Massachusetts",
              "slug": "massachusetts",
              "state-abbreviation": "MA",
              "active": "Yes"
            }
          },
          {
            "id": "6903f2bd20ae3bdd56fff5f8",
            "fieldData": {
              "name": "Michigan",
              "slug": "michigan",
              "state-abbreviation": "MI",
              "active": "Yes"
            }
          },
          {
            "id": "6903f2bd5cee3202d3a86216",
            "fieldData": {
              "name": "Minnesota",
              "slug": "minnesota",
              "state-abbreviation": "MN",
              "active": "Yes"
            }
          },
          {
            "id": "6903f2bd827c379de3877852",
            "fieldData": {
              "name": "Mississippi",
              "slug": "mississippi",
              "state-abbreviation": "MS",
              "active": "Yes"
            }
          },
          {
            "id": "6903f2bde0e9a3a8b49d1c00",
            "fieldData": {
              "name": "Missouri",
              "slug": "missouri",
              "state-abbreviation": "MO",
              "active": "Yes"
            }
          },
          {
            "id": "6903f2bd40340dc5b8303ead",
            "fieldData": {
              "name": "Montana",
              "slug": "montana",
              "state-abbreviation": "MT",
              "active": "Yes"
            }
          },
          {
            "id": "6903f2bdc2767c1cfcefbe14",
            "fieldData": {
              "name": "Nebraska",
              "slug": "nebraska",
              "state-abbreviation": "NE",
              "active": "Yes"
            }
          },
          {
            "id": "6903f2bd48200d6f9a3a7d18",
            "fieldData": {
              "name": "Nevada",
              "slug": "nevada",
              "state-abbreviation": "NV",
              "active": "Yes"
            }
          },
          {
            "id": "6903f2bd9fa35324e9478660",
            "fieldData": {
              "name": "New Hampshire",
              "slug": "new-hampshire",
              "state-abbreviation": "NH",
              "active": "Yes"
            }
          },
          {
            "id": "6903f2bd60250949cc3d209e",
            "fieldData": {
              "name": "New Jersey",
              "slug": "new-jersey",
              "state-abbreviation": "NJ",
              "active": "Yes"
            }
          },
          {
            "id": "6903f2be32cd0383c1a917d9",
            "fieldData": {
              "name": "New Mexico",
              "slug": "new-mexico",
              "state-abbreviation": "NM",
              "active": "Yes"
            }
          },
          {
            "id": "6903f2be19084901c564d9a4",
            "fieldData": {
              "name": "New York",
              "slug": "new-york",
              "state-abbreviation": "NY",
              "active": "Yes"
            }
          },
          {
            "id": "6903f2be2fcf06c4e16ebd4f",
            "fieldData": {
              "name": "North Carolina",
              "slug": "north-carolina",
              "state-abbreviation": "NC",
              "active": "Yes"
            }
          },
          {
            "id": "6903f2be61142e081750706c",
            "fieldData": {
              "name": "North Dakota",
              "slug": "north-dakota",
              "state-abbreviation": "ND",
              "active": "Yes"
            }
          },
          {
            "id": "6903f2be9e65e9f74cfb6b67",
            "fieldData": {
              "name": "Ohio",
              "slug": "ohio",
              "state-abbreviation": "OH",
              "active": "Yes"
            }
          },
          {
            "id": "6903f2be9213990f0ad65019",
            "fieldData": {
              "name": "Oklahoma",
              "slug": "oklahoma",
              "state-abbreviation": "OK",
              "active": "Yes"
            }
          },
          {
            "id": "6903f2be9604bc2c1c1f7dc4",
            "fieldData": {
              "name": "Oregon",
              "slug": "oregon",
              "state-abbreviation": "OR",
              "active": "Yes"
            }
          },
          {
            "id": "6903f2be0bb690eff3c64cdd",
            "fieldData": {
              "name": "Pennsylvania",
              "slug": "pennsylvania",
              "state-abbreviation": "PA",
              "active": "Yes"
            }
          },
          {
            "id": "6903f2be5df5ceda85074381",
            "fieldData": {
              "name": "Rhode Island",
              "slug": "rhode-island",
              "state-abbreviation": "RI",
              "active": "Yes"
            }
          },
          {
            "id": "6903f2bebc43d69b8f8b0f68",
            "fieldData": {
              "name": "South Carolina",
              "slug": "south-carolina",
              "state-abbreviation": "SC",
              "active": "Yes"
            }
          },
          {
            "id": "6903f2be25d6e2bb6c831e79",
            "fieldData": {
              "name": "South Dakota",
              "slug": "south-dakota",
              "state-abbreviation": "SD",
              "active": "Yes"
            }
          },
          {
            "id": "6903f2bee8d5e1e23e9274ec",
            "fieldData": {
              "name": "Tennessee",
              "slug": "tennessee",
              "state-abbreviation": "TN",
              "active": "Yes"
            }
          },
          {
            "id": "6903f2bebe56e1dec2b6feb7",
            "fieldData": {
              "name": "Texas",
              "slug": "texas",
              "state-abbreviation": "TX",
              "active": "Yes"
            }
          },
          {
            "id": "6903f2be195362e21e7a93f5",
            "fieldData": {
              "name": "Utah",
              "slug": "utah",
              "state-abbreviation": "UT",
              "active": "Yes"
            }
          },
          {
            "id": "6903f2bf9c8480cffc346452",
            "fieldData": {
              "name": "Vermont",
              "slug": "vermont",
              "state-abbreviation": "VT",
              "active": "Yes"
            }
          },
          {
            "id": "6903f2bfb983bbec7b5de38c",
            "fieldData": {
              "name": "Virginia",
              "slug": "virginia",
              "state-abbreviation": "VA",
              "active": "Yes"
            }
          },
          {
            "id": "6903f2bf41ac77c86569dcf7",
            "fieldData": {
              "name": "Washington",
              "slug": "washington",
              "state-abbreviation": "WA",
              "active": "Yes"
            }
          },
          {
            "id": "6903f2bfbe56e1dec2b6fedb",
            "fieldData": {
              "name": "West Virginia",
              "slug": "west-virginia",
              "state-abbreviation": "WV",
              "active": "Yes"
            }
          },
          {
            "id": "6903f2bf61142e081750708c",
            "fieldData": {
              "name": "Wisconsin",
              "slug": "wisconsin",
              "state-abbreviation": "WI",
              "active": "Yes"
            }
          },
          {
            "id": "6903f2bf3b657f1931ea61c7",
            "fieldData": {
              "name": "Wyoming",
              "slug": "wyoming",
              "state-abbreviation": "WY",
              "active": "Yes"
            }
          }
        ]
      }
    },
    {
      "id": "6903f50f9b69a380ccd7c23d",
      "fieldData": {
        "name": "St. Luke's Health Plan",
        "slug": "st-lukes-health-plan",
        "coverage-type": "Insurance",
        "payer-parameter": "",
        "insurance-directory-slug": "st_lukes_health_plan",
        "coverage-notes": "",
        "is-insurance-census-less": "No",
        "requires-state-confirmation": "Yes",
        "require-state": "Yes",
        "supported-states": [
          {
            "id": "6903f2bcab773ab938af6932",
            "fieldData": {
              "name": "Idaho",
              "slug": "idaho",
              "state-abbreviation": "ID",
              "active": "Yes"
            }
          }
        ]
      }
    },
    {
      "id": "6903f466c9e466f6a459b6b2",
      "fieldData": {
        "name": "Triwest",
        "slug": "triwest",
        "coverage-type": "Insurance",
        "payer-parameter": "triwest",
        "insurance-directory-slug": "",
        "coverage-notes": "",
        "is-insurance-census-less": "Yes",
        "requires-state-confirmation": "No",
        "require-state": "No",
        "supported-states": []
      }
    }
  ],
  "coverageStateMap": [
    {
      "id": "6903f2bb61067fc1c6d7fb6e",
      "fieldData": {
        "name": "Alabama",
        "slug": "alabama",
        "state-abbreviation": "AL",
        "active": "Yes"
      }
    },
    {
      "id": "6903f2bba5cea9e46a1b81a0",
      "fieldData": {
        "name": "Alaska",
        "slug": "alaska",
        "state-abbreviation": "AK",
        "active": "Yes"
      }
    },
    {
      "id": "6903f2bb1d424b4a1a376d34",
      "fieldData": {
        "name": "Arizona",
        "slug": "arizona",
        "state-abbreviation": "AZ",
        "active": "Yes"
      }
    },
    {
      "id": "6903f2bbca460d320710a892",
      "fieldData": {
        "name": "Arkansas",
        "slug": "arkansas",
        "state-abbreviation": "AR",
        "active": "Yes"
      }
    },
    {
      "id": "6903f2bb5ff0e3f9d4ab016f",
      "fieldData": {
        "name": "California",
        "slug": "california",
        "state-abbreviation": "CA",
        "active": "Yes"
      }
    },
    {
      "id": "6903f2bb99b332631b236e96",
      "fieldData": {
        "name": "Colorado",
        "slug": "colorado",
        "state-abbreviation": "CO",
        "active": "Yes"
      }
    },
    {
      "id": "6903f2bb99664e0c44ef277e",
      "fieldData": {
        "name": "Connecticut",
        "slug": "connecticut",
        "state-abbreviation": "CT",
        "active": "Yes"
      }
    },
    {
      "id": "6903f2bbcd5ca7439133df56",
      "fieldData": {
        "name": "Delaware",
        "slug": "delaware",
        "state-abbreviation": "DE",
        "active": "Yes"
      }
    },
    {
      "id": "6903f2bc65f00e82f49cf2e1",
      "fieldData": {
        "name": "Florida",
        "slug": "florida",
        "state-abbreviation": "FL",
        "active": "Yes"
      }
    },
    {
      "id": "6903f2bc8e3d219e4a3e1726",
      "fieldData": {
        "name": "Georgia",
        "slug": "georgia",
        "state-abbreviation": "GA",
        "active": "Yes"
      }
    },
    {
      "id": "6903f2bc13541897ea4b4b46",
      "fieldData": {
        "name": "Hawaii",
        "slug": "hawaii",
        "state-abbreviation": "HI",
        "active": "Yes"
      }
    },
    {
      "id": "6903f2bcab773ab938af6932",
      "fieldData": {
        "name": "Idaho",
        "slug": "idaho",
        "state-abbreviation": "ID",
        "active": "Yes"
      }
    },
    {
      "id": "6903f2bc0bb690eff3c64cae",
      "fieldData": {
        "name": "Illinois",
        "slug": "illinois",
        "state-abbreviation": "IL",
        "active": "Yes"
      }
    },
    {
      "id": "6903f2bce0e9a3a8b49d1ba7",
      "fieldData": {
        "name": "Indiana",
        "slug": "indiana",
        "state-abbreviation": "IN",
        "active": "Yes"
      }
    },
    {
      "id": "6903f2bce3db62b4cd45cd59",
      "fieldData": {
        "name": "Iowa",
        "slug": "iowa",
        "state-abbreviation": "IA",
        "active": "Yes"
      }
    },
    {
      "id": "6903f2bc560c699c97edcb89",
      "fieldData": {
        "name": "Kansas",
        "slug": "kansas",
        "state-abbreviation": "KS",
        "active": "Yes"
      }
    },
    {
      "id": "6903f2bc144e670775c51faf",
      "fieldData": {
        "name": "Kentucky",
        "slug": "kentucky",
        "state-abbreviation": "KY",
        "active": "Yes"
      }
    },
    {
      "id": "6903f2bcd657eab6424a41a6",
      "fieldData": {
        "name": "Louisiana",
        "slug": "louisiana",
        "state-abbreviation": "LA",
        "active": "Yes"
      }
    },
    {
      "id": "6903f2bc33a9c63289784a1e",
      "fieldData": {
        "name": "Maine",
        "slug": "maine",
        "state-abbreviation": "ME",
        "active": "Yes"
      }
    },
    {
      "id": "6903f2bceee62ad401683ca3",
      "fieldData": {
        "name": "Maryland",
        "slug": "maryland",
        "state-abbreviation": "MD",
        "active": "Yes"
      }
    },
    {
      "id": "6903f2bc1c1d5520d5cd133a",
      "fieldData": {
        "name": "Massachusetts",
        "slug": "massachusetts",
        "state-abbreviation": "MA",
        "active": "Yes"
      }
    },
    {
      "id": "6903f2bd20ae3bdd56fff5f8",
      "fieldData": {
        "name": "Michigan",
        "slug": "michigan",
        "state-abbreviation": "MI",
        "active": "Yes"
      }
    },
    {
      "id": "6903f2bd5cee3202d3a86216",
      "fieldData": {
        "name": "Minnesota",
        "slug": "minnesota",
        "state-abbreviation": "MN",
        "active": "Yes"
      }
    },
    {
      "id": "6903f2bd827c379de3877852",
      "fieldData": {
        "name": "Mississippi",
        "slug": "mississippi",
        "state-abbreviation": "MS",
        "active": "Yes"
      }
    },
    {
      "id": "6903f2bde0e9a3a8b49d1c00",
      "fieldData": {
        "name": "Missouri",
        "slug": "missouri",
        "state-abbreviation": "MO",
        "active": "Yes"
      }
    },
    {
      "id": "6903f2bd40340dc5b8303ead",
      "fieldData": {
        "name": "Montana",
        "slug": "montana",
        "state-abbreviation": "MT",
        "active": "Yes"
      }
    },
    {
      "id": "6903f2bdc2767c1cfcefbe14",
      "fieldData": {
        "name": "Nebraska",
        "slug": "nebraska",
        "state-abbreviation": "NE",
        "active": "Yes"
      }
    },
    {
      "id": "6903f2bd48200d6f9a3a7d18",
      "fieldData": {
        "name": "Nevada",
        "slug": "nevada",
        "state-abbreviation": "NV",
        "active": "Yes"
      }
    },
    {
      "id": "6903f2bd9fa35324e9478660",
      "fieldData": {
        "name": "New Hampshire",
        "slug": "new-hampshire",
        "state-abbreviation": "NH",
        "active": "Yes"
      }
    },
    {
      "id": "6903f2bd60250949cc3d209e",
      "fieldData": {
        "name": "New Jersey",
        "slug": "new-jersey",
        "state-abbreviation": "NJ",
        "active": "Yes"
      }
    },
    {
      "id": "6903f2be32cd0383c1a917d9",
      "fieldData": {
        "name": "New Mexico",
        "slug": "new-mexico",
        "state-abbreviation": "NM",
        "active": "Yes"
      }
    },
    {
      "id": "6903f2be19084901c564d9a4",
      "fieldData": {
        "name": "New York",
        "slug": "new-york",
        "state-abbreviation": "NY",
        "active": "Yes"
      }
    },
    {
      "id": "6903f2be2fcf06c4e16ebd4f",
      "fieldData": {
        "name": "North Carolina",
        "slug": "north-carolina",
        "state-abbreviation": "NC",
        "active": "Yes"
      }
    },
    {
      "id": "6903f2be61142e081750706c",
      "fieldData": {
        "name": "North Dakota",
        "slug": "north-dakota",
        "state-abbreviation": "ND",
        "active": "Yes"
      }
    },
    {
      "id": "6903f2be9e65e9f74cfb6b67",
      "fieldData": {
        "name": "Ohio",
        "slug": "ohio",
        "state-abbreviation": "OH",
        "active": "Yes"
      }
    },
    {
      "id": "6903f2be9213990f0ad65019",
      "fieldData": {
        "name": "Oklahoma",
        "slug": "oklahoma",
        "state-abbreviation": "OK",
        "active": "Yes"
      }
    },
    {
      "id": "6903f2be9604bc2c1c1f7dc4",
      "fieldData": {
        "name": "Oregon",
        "slug": "oregon",
        "state-abbreviation": "OR",
        "active": "Yes"
      }
    },
    {
      "id": "6903f2be0bb690eff3c64cdd",
      "fieldData": {
        "name": "Pennsylvania",
        "slug": "pennsylvania",
        "state-abbreviation": "PA",
        "active": "Yes"
      }
    },
    {
      "id": "6903f2be5df5ceda85074381",
      "fieldData": {
        "name": "Rhode Island",
        "slug": "rhode-island",
        "state-abbreviation": "RI",
        "active": "Yes"
      }
    },
    {
      "id": "6903f2bebc43d69b8f8b0f68",
      "fieldData": {
        "name": "South Carolina",
        "slug": "south-carolina",
        "state-abbreviation": "SC",
        "active": "Yes"
      }
    },
    {
      "id": "6903f2be25d6e2bb6c831e79",
      "fieldData": {
        "name": "South Dakota",
        "slug": "south-dakota",
        "state-abbreviation": "SD",
        "active": "Yes"
      }
    },
    {
      "id": "6903f2bee8d5e1e23e9274ec",
      "fieldData": {
        "name": "Tennessee",
        "slug": "tennessee",
        "state-abbreviation": "TN",
        "active": "Yes"
      }
    },
    {
      "id": "6903f2bebe56e1dec2b6feb7",
      "fieldData": {
        "name": "Texas",
        "slug": "texas",
        "state-abbreviation": "TX",
        "active": "Yes"
      }
    },
    {
      "id": "6903f2be195362e21e7a93f5",
      "fieldData": {
        "name": "Utah",
        "slug": "utah",
        "state-abbreviation": "UT",
        "active": "Yes"
      }
    },
    {
      "id": "6903f2bf9c8480cffc346452",
      "fieldData": {
        "name": "Vermont",
        "slug": "vermont",
        "state-abbreviation": "VT",
        "active": "Yes"
      }
    },
    {
      "id": "6903f2bfb983bbec7b5de38c",
      "fieldData": {
        "name": "Virginia",
        "slug": "virginia",
        "state-abbreviation": "VA",
        "active": "Yes"
      }
    },
    {
      "id": "6903f2bf41ac77c86569dcf7",
      "fieldData": {
        "name": "Washington",
        "slug": "washington",
        "state-abbreviation": "WA",
        "active": "Yes"
      }
    },
    {
      "id": "6903f2bfbe56e1dec2b6fedb",
      "fieldData": {
        "name": "West Virginia",
        "slug": "west-virginia",
        "state-abbreviation": "WV",
        "active": "Yes"
      }
    },
    {
      "id": "6903f2bf61142e081750708c",
      "fieldData": {
        "name": "Wisconsin",
        "slug": "wisconsin",
        "state-abbreviation": "WI",
        "active": "Yes"
      }
    },
    {
      "id": "6903f2bf3b657f1931ea61c7",
      "fieldData": {
        "name": "Wyoming",
        "slug": "wyoming",
        "state-abbreviation": "WY",
        "active": "Yes"
      }
    }
  ],
  "totalCoverageEntries": 6,
  "totalCoverageStateMap": 50,
  "lastUpdated": "2025-11-14T05:04:13.944Z"
}